[{"doc": "12-years-a-slave-2013", "main_char": "SOLOMON"},
  {"doc": "a-star-is-born-2018", "main_char": "JACK"},
  {"doc": "american-sniper-2014", "main_char": "CHRIS"},
  {"doc": "argo-2012", "main_char": "MENDEZ"},
  {"doc": "before-midnight-2013", "main_char": "JESSE"},
  {"doc": "blackkkklansman-2018", "main_char": "RON STALLWORTH"},
  {"doc": "borat-subsequent-moviefilm-2020", "main_char": "BORAT"},
  {"doc": "brooklyn-2015", "main_char": "EILIS"},
  {"doc": "call-me-by-your-name-2017", "main_char": "OLIVER"},
  {"doc": "can-you-ever-forgive-me-2018", "main_char": "LEE"},
  {"doc": "captain-phillips-2013", "main_char": "PHILLIPS"},
  {"doc": "carol-2015", "main_char": "CAROL"},
  {"doc": "hidden-figures-2016", "main_char": "KATHERINE"},
  {"doc": "hugo-2011", "main_char": "HUGO"},
  {"doc": "if-beale-street-could-talk-2018", "main_char": "FONNY"},
  {"doc": "inherent-vice-2014", "main_char": "DOC"},
  {"doc": "jojo-rabbit-2019", "main_char": "JOJO"},
  {"doc": "joker-2019", "main_char": "JOKER"},
  {"doc": "life-of-pi-2012", "main_char": "PI"},
  {"doc": "lincoln-2012", "main_char": "LINCOLN"},
  {"doc": "lion-2016", "main_char": "SAROO"},
  {"doc": "little-women-2019", "main_char": "JO"},
  {"doc": "logan-2017", "main_char": "LOGAN"},
  {"doc": "logan-2017", "main_char": "LOGAN"},
  {"doc": "moonlight-2016", "main_char": "CHIRON"},
  {"doc": "mudbound-2017", "main_char": "LAURA"},
  {"doc": "nomadland-2020", "main_char": "FERN"},
  {"doc": "one-night-in-miami-2020", "main_char": "MALCOLM"},
  {"doc": "philomena-2013", "main_char": "PHILOMENA"},
  {"doc": "room-2015", "main_char": "MA"},
  {"doc": "silver-linings-playbook-2012", "main_char": "PAT"},
  {"doc": "the-big-short-2015", "main_char": "MICHAEL BURRY"},
  {"doc": "the-descendants-2011", "main_char": "MATT"},
  {"doc": "the-father-2020", "main_char": "ANTHONY"},
  {"doc": "the-imitation-game-2014", "main_char": "ALAN TURING"},
  {"doc": "the-irishman-2019", "main_char": "FRANK"},
  {"doc": "the-martian-2015", "main_char": "MARK"},
  {"doc": "the-social-network-2010", "main_char": "MARK"},
  {"doc": "the-theory-of-everything-2015", "main_char": "STEPHEN"},
  {"doc": "the-white-tiger-2021", "main_char": "BALRAM"},
  {"doc": "the-wolf-of-wall-street-2013", "main_char": "JORDAN"},
  {"doc": "tinker-tailor-soldier-spy-2011", "main_char": "SMILEY"},
  {"doc": "toy-story-3-2010", "main_char": "WOODY"},
  {"doc": "whiplash-2014", "main_char": "ANDREW"},
  {"doc": "winters-bone-2010", "main_char": "REE"}]

